mkite_vasp/__init__.py
mkite_vasp/parsers/__init__.py
mkite_vasp/parsers/bands.py
mkite_vasp/parsers/base.py
mkite_vasp/parsers/dos.py
mkite_vasp/recipes/__init__.py
mkite_vasp/recipes/base.py
mkite_vasp/recipes/errors.py
mkite_vasp/recipes/pipes.py
mkite_vasp/recipes/pbe/__init__.py
mkite_vasp/recipes/pbe/relax.py
mkite_vasp/recipes/pbe/static.py
mkite_vasp/recipes/rpbe/__init__.py
mkite_vasp/recipes/rpbe/dos.py
mkite_vasp/recipes/rpbe/relax.py
mkite_vasp/recipes/rpbe/static.py
mkite_vasp/runners/__init__.py
mkite_vasp/runners/custodian.py
mkite_vasp/settings/__init__.py
mkite_vasp/settings/settings.py
mkite_vasp/tests/__init__.py
mkite_vasp/tests/test_recipe.py
mkite_vasp/tests/test_runner.py
mkite_vasp/tests/test_settings.py
mkite_vasp/tests/files/__init__.py
mkite_vasp-25.11.3.dist-info/licenses/LICENSE
mkite_vasp-25.11.3.dist-info/licenses/NOTICE
mkite_vasp-25.11.3.dist-info/METADATA
mkite_vasp-25.11.3.dist-info/WHEEL
mkite_vasp-25.11.3.dist-info/entry_points.txt
mkite_vasp-25.11.3.dist-info/top_level.txt
mkite_vasp-25.11.3.dist-info/RECORD
