Metadata-Version: 2.4
Name: mkite_vasp
Version: 25.11.3
Summary: mkite_vasp is a plugin to execute VASP calculations using mkite
Author-email: Daniel Schwalbe-Koda <dskoda@ucla.edu>
Keywords: workflow,materials-science
Requires-Python: >=3.8
License-File: LICENSE
License-File: NOTICE
Requires-Dist: pymatgen
Requires-Dist: custodian
Requires-Dist: pydantic>=2.0
Dynamic: license-file
